KratosMultiphysics/.libs/KratosParticleMechanicsApplication.pyd
KratosMultiphysics/.libs/KratosParticleMechanicsCore.dll
KratosMultiphysics/.libs/KratosParticleMechanicsCore.lib
KratosMultiphysics/ParticleMechanicsApplication/__init__.py
KratosMultiphysics/ParticleMechanicsApplication/apply_mpm_3d_rotating_dirichlet_condition_process.py
KratosMultiphysics/ParticleMechanicsApplication/apply_mpm_coupling_interface_dirichlet_condition_process.py
KratosMultiphysics/ParticleMechanicsApplication/apply_mpm_coupling_interface_neumann_condition_process.py
KratosMultiphysics/ParticleMechanicsApplication/apply_mpm_particle_dirichlet_condition_process.py
KratosMultiphysics/ParticleMechanicsApplication/apply_mpm_particle_neumann_condition_process.py
KratosMultiphysics/ParticleMechanicsApplication/apply_mpm_slip_boundary_process.py
KratosMultiphysics/ParticleMechanicsApplication/assign_gravity_to_particle_process.py
KratosMultiphysics/ParticleMechanicsApplication/assign_initial_velocity_to_particle_process.py
KratosMultiphysics/ParticleMechanicsApplication/kratos_main_particle.py
KratosMultiphysics/ParticleMechanicsApplication/mpm_explicit_solver.py
KratosMultiphysics/ParticleMechanicsApplication/mpm_implicit_dynamic_solver.py
KratosMultiphysics/ParticleMechanicsApplication/mpm_quasi_static_solver.py
KratosMultiphysics/ParticleMechanicsApplication/mpm_solver.py
KratosMultiphysics/ParticleMechanicsApplication/mpm_static_solver.py
KratosMultiphysics/ParticleMechanicsApplication/particle_from_json_check_result_process.py
KratosMultiphysics/ParticleMechanicsApplication/particle_gid_output_process.py
KratosMultiphysics/ParticleMechanicsApplication/particle_json_output_process.py
KratosMultiphysics/ParticleMechanicsApplication/particle_mechanics_analysis.py
KratosMultiphysics/ParticleMechanicsApplication/particle_vtk_condition_output_process.py
KratosMultiphysics/ParticleMechanicsApplication/particle_vtk_output_process.py
KratosParticleMechanicsApplication-9.4.6.dist-info/METADATA
KratosParticleMechanicsApplication-9.4.6.dist-info/WHEEL
KratosParticleMechanicsApplication-9.4.6.dist-info/top_level.txt
KratosParticleMechanicsApplication-9.4.6.dist-info/RECORD
